analyses/__init__.py
analyses/admin.py
analyses/apps.py
analyses/forms.py
analyses/models.py
analyses/tasks.py
analyses/tests.py
analyses/urls.py
analyses/views.py
analyses/migrations/0001_initial.py
analyses/migrations/__init__.py
blog/__init__.py
blog/admin.py
blog/apps.py
blog/models.py
blog/tests.py
blog/views.py
blog/migrations/__init__.py
cases/__init__.py
cases/admin.py
cases/forms.py
cases/models.py
cases/tests.py
cases/urls.py
cases/views.py
cases/migrations/0001_initial.py
cases/migrations/__init__.py
dashboard/__init__.py
dashboard/admin.py
dashboard/models.py
dashboard/tests.py
dashboard/urls.py
dashboard/views.py
databases/__init__.py
databases/forms.py
databases/models.py
databases/tests.py
databases/urls.py
databases/views.py
databases/management/__init__.py
databases/management/commands/__init__.py
databases/management/commands/_private.py
databases/management/commands/celery.py
databases/management/commands/extract_individuals.py
databases/management/commands/import_1000genomes.py
databases/management/commands/import_dbnfsp.py
databases/management/commands/import_hgmd.py
databases/management/commands/populate.py
databases/management/commands/populate_varisnp.py
databases/migrations/0001_initial.py
databases/migrations/__init__.py
diseases/__init__.py
diseases/models.py
diseases/tests.py
diseases/urls.py
diseases/views.py
diseases/migrations/0001_initial.py
diseases/migrations/__init__.py
django_select2/__init__.py
django_select2/cache.py
django_select2/conf.py
django_select2/forms.py
django_select2/models.py
django_select2/urls.py
django_select2/views.py
files/__init__.py
files/admin.py
files/apps.py
files/forms.py
files/models.py
files/tasks.py
files/tests.py
files/urls.py
files/views.py
files/management/__init__.py
files/management/commands/__init__.py
files/management/commands/download_files.py
files/management/commands/import_files.py
files/management/commands/update_files.py
files/migrations/0001_initial.py
files/migrations/__init__.py
mendelmd-1.2.4.dist-info/LICENSE
mendelmd-1.2.4.dist-info/METADATA
mendelmd-1.2.4.dist-info/WHEEL
mendelmd-1.2.4.dist-info/top_level.txt
mendelmd-1.2.4.dist-info/RECORD
